<annotation>
	<folder></folder>
	<filename>img-405_jpg.rf.00cc69b098d87655ac30746a9f5af803.jpg</filename>
	<path>img-405_jpg.rf.00cc69b098d87655ac30746a9f5af803.jpg</path>
	<source>
		<database>roboflow.ai</database>
	</source>
	<size>
		<width>640</width>
		<height>640</height>
		<depth>3</depth>
	</size>
	<segmented>0</segmented>
	<object>
		<name>Pothole</name>
		<pose>Unspecified</pose>
		<truncated>0</truncated>
		<difficult>0</difficult>
		<occluded>0</occluded>
		<bndbox>
			<xmin>124</xmin>
			<xmax>305</xmax>
			<ymin>428</ymin>
			<ymax>637</ymax>
		</bndbox>
	</object>
	<object>
		<name>Pothole</name>
		<pose>Unspecified</pose>
		<truncated>0</truncated>
		<difficult>0</difficult>
		<occluded>0</occluded>
		<bndbox>
			<xmin>1</xmin>
			<xmax>209</xmax>
			<ymin>221</ymin>
			<ymax>362</ymax>
		</bndbox>
	</object>
	<object>
		<name>Pothole</name>
		<pose>Unspecified</pose>
		<truncated>0</truncated>
		<difficult>0</difficult>
		<occluded>0</occluded>
		<bndbox>
			<xmin>211</xmin>
			<xmax>277</xmax>
			<ymin>263</ymin>
			<ymax>321</ymax>
		</bndbox>
	</object>
	<object>
		<name>Pothole</name>
		<pose>Unspecified</pose>
		<truncated>0</truncated>
		<difficult>0</difficult>
		<occluded>0</occluded>
		<bndbox>
			<xmin>312</xmin>
			<xmax>501</xmax>
			<ymin>332</ymin>
			<ymax>484</ymax>
		</bndbox>
	</object>
	<object>
		<name>Pothole</name>
		<pose>Unspecified</pose>
		<truncated>0</truncated>
		<difficult>0</difficult>
		<occluded>0</occluded>
		<bndbox>
			<xmin>324</xmin>
			<xmax>497</xmax>
			<ymin>236</ymin>
			<ymax>319</ymax>
		</bndbox>
	</object>
	<object>
		<name>Pothole</name>
		<pose>Unspecified</pose>
		<truncated>0</truncated>
		<difficult>0</difficult>
		<occluded>0</occluded>
		<bndbox>
			<xmin>390</xmin>
			<xmax>483</xmax>
			<ymin>178</ymin>
			<ymax>223</ymax>
		</bndbox>
	</object>
	<object>
		<name>Pothole</name>
		<pose>Unspecified</pose>
		<truncated>0</truncated>
		<difficult>0</difficult>
		<occluded>0</occluded>
		<bndbox>
			<xmin>254</xmin>
			<xmax>336</xmax>
			<ymin>170</ymin>
			<ymax>204</ymax>
		</bndbox>
	</object>
	<object>
		<name>Pothole</name>
		<pose>Unspecified</pose>
		<truncated>0</truncated>
		<difficult>0</difficult>
		<occluded>0</occluded>
		<bndbox>
			<xmin>589</xmin>
			<xmax>640</xmax>
			<ymin>347</ymin>
			<ymax>415</ymax>
		</bndbox>
	</object>
</annotation>
